README.md
pyproject.toml
setup.cfg
setup.py
examples/mountainsort4_example1.py
mountainsort4/__init__.py
mountainsort4/_mdaio_impl.py
mountainsort4/mountainsort4.py
mountainsort4/ms4alg.py
mountainsort4/version.py
mountainsort4.egg-info/PKG-INFO
mountainsort4.egg-info/SOURCES.txt
mountainsort4.egg-info/dependency_links.txt
mountainsort4.egg-info/requires.txt
mountainsort4.egg-info/top_level.txt